awsLogger/CustomLogger.py
awsLogger/__init__.py
awsLogger-0.0.9.dist-info/DESCRIPTION.rst
awsLogger-0.0.9.dist-info/METADATA
awsLogger-0.0.9.dist-info/RECORD
awsLogger-0.0.9.dist-info/WHEEL
awsLogger-0.0.9.dist-info/metadata.json
awsLogger-0.0.9.dist-info/top_level.txt
