Metadata-Version: 2.0
Name: awsLogger
Version: 0.0.9
Summary: log into a file and push it to aws s3
Home-page: https://github.com/pypa/example-project
Author: guillaume ringwald
Author-email: gring.fr@gmail.com
License: UNKNOWN
Platform: UNKNOWN
Classifier: Programming Language :: Python :: 3
Classifier: License :: OSI Approved :: MIT License
Classifier: Operating System :: OS Independent
Requires-Dist: boto3
